cqupt/__init__.py
cqupt/auth.py
cqupt/error.py
cqupt/fs.py
cqupt/log.py
cqupt/piper.py
cqupt/request.py
cqupt/urls.py
cqupt/crawlers/__init__.py
cqupt/crawlers/credit.py
cqupt/crawlers/fee.py
cqupt/crawlers/gpa.py
cqupt/crawlers/photo.py
cqupt/crawlers/task.py
cqupt-0.1.2.dist-info/LICENSE
cqupt-0.1.2.dist-info/METADATA
cqupt-0.1.2.dist-info/WHEEL
cqupt-0.1.2.dist-info/entry_points.txt
cqupt-0.1.2.dist-info/top_level.txt
cqupt-0.1.2.dist-info/RECORD
