Metadata-Version: 2.1
Name: cqupt
Version: 0.1.2
Summary: CQUPT Piper is a command line tool to get info from jwzx.cqupt.edu.cn
Home-page: https://github.com/mivinci/cqupt-piper
Author: Mivinci XJJ
License: UNKNOWN
Platform: UNKNOWN
Requires-Python: >=3.5
Requires-Dist: PrettyTable
Requires-Dist: Pillow
Requires-Dist: requests
Requires-Dist: bs4
